Archive/WiSe_2022_2023/TechnischeInformatik/submissions/submission_22_11_21_dressler_kroehl_halank/src/xor_3.sv
/**
 *3 Input xor (because we don't use bitwise operators apperantly)
 **/
module xor_3 ( input  logic i_in0,
                            i_in1,
                            i_in2,
               output logic o_res );
    logic l_xor0;
    xor xor_0 (l_xor0, i_in0, i_in1);
    xor xor_1 (o_res, l_xor0, i_in2);
endmodule

Archive/WiSe_2022_2023/TechnischeInformatik/submissions/submission_22_11_28_dressler_kroehl_halank/src/mux_2.sv
/**
 *2er Mux für N bits
 **/
module mux_2 #(parameter N=64) ( input  logic [N-1:0] i_in0,
                                                   i_in1,
                              input  logic         i_s,
                              output logic [N-1:0] o_out );
    always_comb
    begin
        case(i_s)
            1'b0: o_out = i_in0;
            1'b1: o_out = i_in1;
            default: o_out = 1'bx;
        endcase
    end

endmodule

Archive/WiSe_2022_2023/TechnischeInformatik/submissions/submission_22_11_21_dressler_kroehl_halank/src/mux_4.sv
/**
 *4er Mux für N bits
 **/
module mux_4 #(parameter N=64) (input  logic [N-1:0]    i_in0,
                                                        i_in1,
                                                        i_in2,
                                                        i_in3,
                                input  logic [1:0]      i_s,
                                output logic [N-1:0]    o_out );
    logic [N-1:0] l_out0;
    logic [N-1:0] l_out1;

    mux_2 #(.N(N)) mux_2_0 ( .i_in0 ( i_in0 ),
                            .i_in1 ( i_in1 ),
                            .i_s   ( i_s[0] ),
                            .o_out ( l_out0 ) );

    mux_2 #(.N(N)) mux_2_1 ( .i_in0 ( i_in2 ),
                            .i_in1 ( i_in3 ),
                            .i_s   ( i_s[0] ),
                            .o_out ( l_out1 ) );

    mux_2 #(.N(N)) mux_2_2 ( .i_in0 ( l_out0 ),
                            .i_in1 ( l_out1 ),
                            .i_s   ( i_s[1] ),
                            .o_out ( o_out ) );
endmodule

Archive/WiSe_2022_2023/TechnischeInformatik/submissions/submission_22_11_21_dressler_kroehl_halank/src/adder.sv
/**
 *N Bit Adder
 **/
module adder #(parameter N=64) (input  logic    [N-1:0] i_a,
                                                i_b,
                                input  logic    i_carry_in,
                                output logic    [N-1:0] o_s,
                                output logic    o_carry_out );
    assign {o_carry_out,o_s} = i_a + i_b + i_carry_in;

endmodule

Archive/WiSe_2022_2023/TechnischeInformatik/submissions/submission_22_11_21_dressler_kroehl_halank/src/alu_nzcv.sv
module alu_nzcv #(parameter N=64) ( input  logic [N-1:0] i_a,
                                                      i_b,
                                 input  logic [1:0]   i_alu_ctrl,
                                 output logic [N-1:0] o_result,
                                 output logic [3:0]   o_nzcv );
    logic l_carry_out, l_not_alu_ctrl, l_xor,l_xor_3, l_nxor_3, l_and_overflow;
    logic [N-1:0] l_mux, l_adder, l_and, l_or, l_notb;


    assign l_notb = ~i_b;
    assign l_and  = i_a & i_b;
    assign l_or   = i_a | i_b;
    mux_2 #(.N(N)) mux_2_0(.i_s(i_alu_ctrl[0:0]), .i_in0(i_b), .i_in1(l_notb), .o_out(l_mux));
    adder #(.N(N)) adder_0(.i_a(i_a), .i_b(l_mux),.i_carry_in(i_alu_ctrl[0:0]), .o_s(l_adder), .o_carry_out(l_carry_out));
    mux_4 #(.N(N)) mux_4_0(.i_s(i_alu_ctrl), .i_in0(l_adder), .i_in1(l_adder), .i_in2(l_and), .i_in3(l_or), .o_out(o_result));

    //negative Flag
    assign o_nzcv[3] = o_result[N-1:N-1];

    //zero Flag
    assign o_nzcv[2] = (o_result[N-1:0] == 0);

    //carry flag
    not not_0(l_not_alu_ctrl, i_alu_ctrl[1:1]);
    and and_0(o_nzcv[1], l_not_alu_ctrl, l_carry_out);

    //overflow flag
    xor xor_0(l_xor, i_a[N-1:N-1], l_adder[N-1:N-1]);
    xor_3 xor_3_0(.o_res(l_xor_3), .i_in0(i_a[N-1:N-1]), .i_in1(i_b[N-1:N-1]), .i_in2(i_alu_ctrl[0:0]));
    not not_3_0(l_nxor_3, l_xor_3);
    and and_1(l_and_overflow, l_xor, l_nxor_3);
    and and_2(o_nzcv[0], l_not_alu_ctrl, l_and_overflow);

endmodule

Archive/WiSe_2022_2023/TechnischeInformatik/submissions/submission_22_11_21_dressler_kroehl_halank/src/alu_nzcv_tb.sv
/**
 *Testbench for ALU with Flags
 **/
module alu_nzcv_tb;
    logic [31:0] l_a, l_b, l_result;
    logic [1:0] l_alu_ctrl;
    logic [3:0] l_nzcv;

    alu_nzcv #(.N(32)) m_dut(.i_a(l_a), .i_b(l_b), .i_alu_ctrl(l_alu_ctrl), .o_result(l_result), .o_nzcv(l_nzcv));

    initial begin
        $dumpfile("alu_nzcv_tb.vcd");
        $dumpvars;
        l_a = 32'h0000_0000;
        l_b = 32'h0000_0000;
        l_alu_ctrl = 2'b00;
        #10;
        assert(l_result === 32'h0000_0000);
        assert(l_nzcv === 4'b0100);

        l_a = 32'h0000_0000;
        l_b = 32'hffff_ffff;
        l_alu_ctrl = 2'b00;
        #10;
        assert(l_result === 32'hffff_ffff);
        assert(l_nzcv === 4'b1000);

        l_a = 32'h0000_0001;
        l_b = 32'hffff_ffff;
        l_alu_ctrl = 2'b00;
        #10;
        assert(l_result === 32'h0000_0000);
        assert(l_nzcv === 4'b0110);

        l_a = 32'h0000_ffff;
        l_b = 32'h0000_0001;
        l_alu_ctrl = 2'b00;
        #10;
        assert(l_result === 32'h0001_0000);
        assert(l_nzcv === 4'b0000);

        l_a = 32'h0000_0000;
        l_b = 32'h0000_0000;
        l_alu_ctrl = 2'b01;
        #10;
        assert(l_result === 32'h0000_0000);
        assert(l_nzcv === 4'b0110);

        l_a = 32'h0001_0000;
        l_b = 32'h0000_0001;
        l_alu_ctrl = 2'b01;
        #10;
        assert(l_result === 32'h0000_ffff);
        assert(l_nzcv === 4'b0010);

        l_a = 32'hffff_ffff;
        l_b = 32'hffff_ffff;
        l_alu_ctrl = 2'b10;
        #10;
        assert(l_result === 32'hffff_ffff);
        assert(l_nzcv === 4'b1000);

        l_a = 32'hffff_ffff;
        l_b = 32'h7743_3477;
        l_alu_ctrl = 2'b10;
        #10;
        assert(l_result === 32'h7743_3477);
        assert(l_nzcv === 4'b0000);

        l_a = 32'h0000_0000;
        l_b = 32'hffff_ffff;
        l_alu_ctrl = 2'b10;
        #10;
        assert(l_result === 32'h0000_0000);
        assert(l_nzcv === 4'b0100);

        l_a = 32'h0000_0000;
        l_b = 32'hffff_ffff;
        l_alu_ctrl = 2'b11;
        #10;
        assert(l_result === 32'hffff_ffff);
        assert(l_nzcv === 4'b1000);

        $finish;
    end
endmodule

Archive/WiSe_2022_2023/TechnischeInformatik/submissions/submission_22_11_21_dressler_kroehl_halank/src/alu_nzcv_tb.vcd
$date
	Tue Nov 15 17:37:39 2022
$end
$version
	Icarus Verilog
$end
$timescale
	1s
$end
$scope module alu_nzcv_tb $end
$var wire 32 ! l_result [31:0] $end
$var wire 4 " l_nzcv [3:0] $end
$var reg 32 # l_a [31:0] $end
$var reg 2 $ l_alu_ctrl [1:0] $end
$var reg 32 % l_b [31:0] $end
$scope module m_dut $end
$var wire 32 & i_a [31:0] $end
$var wire 2 ' i_alu_ctrl [1:0] $end
$var wire 32 ( i_b [31:0] $end
$var wire 32 ) l_and [31:0] $end
$var wire 1 * l_and_overflow $end
$var wire 1 + l_not_alu_ctrl $end
$var wire 32 , l_notb [31:0] $end
$var wire 1 - l_nxor_3 $end
$var wire 32 . l_or [31:0] $end
$var wire 1 / l_xor $end
$var wire 32 0 o_result [31:0] $end
$var wire 4 1 o_nzcv [3:0] $end
$var wire 1 2 l_xor_3 $end
$var wire 32 3 l_mux [31:0] $end
$var wire 1 4 l_carry_out $end
$var wire 32 5 l_adder [31:0] $end
$scope module adder_0 $end
$var wire 32 6 i_a [31:0] $end
$var wire 1 7 i_carry_in $end
$var wire 32 8 o_s [31:0] $end
$var wire 1 4 o_carry_out $end
$var wire 32 9 i_b [31:0] $end
$upscope $end
$scope module mux_2_0 $end
$var wire 32 : i_in0 [31:0] $end
$var wire 32 ; i_in1 [31:0] $end
$var wire 1 < i_s $end
$var reg 32 = o_out [31:0] $end
$upscope $end
$scope module mux_4_0 $end
$var wire 32 > i_in0 [31:0] $end
$var wire 32 ? i_in1 [31:0] $end
$var wire 32 @ i_in2 [31:0] $end
$var wire 32 A i_in3 [31:0] $end
$var wire 2 B i_s [1:0] $end
$var wire 32 C o_out [31:0] $end
$var wire 32 D l_out1 [31:0] $end
$var wire 32 E l_out0 [31:0] $end
$scope module mux_2_0 $end
$var wire 32 F i_in0 [31:0] $end
$var wire 32 G i_in1 [31:0] $end
$var wire 1 H i_s $end
$var reg 32 I o_out [31:0] $end
$upscope $end
$scope module mux_2_1 $end
$var wire 32 J i_in0 [31:0] $end
$var wire 32 K i_in1 [31:0] $end
$var wire 1 L i_s $end
$var reg 32 M o_out [31:0] $end
$upscope $end
$scope module mux_2_2 $end
$var wire 32 N i_in0 [31:0] $end
$var wire 32 O i_in1 [31:0] $end
$var wire 1 P i_s $end
$var reg 32 Q o_out [31:0] $end
$upscope $end
$upscope $end
$scope module xor_3_0 $end
$var wire 1 R i_in0 $end
$var wire 1 S i_in1 $end
$var wire 1 T i_in2 $end
$var wire 1 U l_xor0 $end
$var wire 1 2 o_res $end
$upscope $end
$upscope $end
$upscope $end
$enddefinitions $end
#0
$dumpvars
0U
0T
0S
0R
b0 Q
0P
b0 O
b0 N
b0 M
0L
b0 K
b0 J
b0 I
0H
b0 G
b0 F
b0 E
b0 D
b0 C
b0 B
b0 A
b0 @
b0 ?
b0 >
b0 =
0<
b11111111111111111111111111111111 ;
b0 :
b0 9
b0 8
07
b0 6
b0 5
04
b0 3
02
b100 1
b0 0
0/
b0 .
1-
b11111111111111111111111111111111 ,
1+
0*
b0 )
b0 (
b0 '
b0 &
b0 %
b0 $
b0 #
b100 "
b0 !
$end
#10
0-
1/
b1000 "
b1000 1
b11111111111111111111111111111111 !
b11111111111111111111111111111111 0
b11111111111111111111111111111111 C
b11111111111111111111111111111111 Q
12
b11111111111111111111111111111111 E
b11111111111111111111111111111111 I
b11111111111111111111111111111111 N
1U
b11111111111111111111111111111111 5
b11111111111111111111111111111111 8
b11111111111111111111111111111111 >
b11111111111111111111111111111111 ?
b11111111111111111111111111111111 F
b11111111111111111111111111111111 G
b0 ,
b0 ;
b11111111111111111111111111111111 .
b11111111111111111111111111111111 A
b11111111111111111111111111111111 K
1S
b11111111111111111111111111111111 3
b11111111111111111111111111111111 9
b11111111111111111111111111111111 =
b11111111111111111111111111111111 %
b11111111111111111111111111111111 (
b11111111111111111111111111111111 :
#20
0/
b0 !
b0 0
b0 C
b0 Q
b1 D
b1 M
b1 O
b0 E
b0 I
b0 N
b110 "
b110 1
b1 )
b1 @
b1 J
b0 5
b0 8
b0 >
b0 ?
b0 F
b0 G
14
b1 #
b1 &
b1 6
#30
1-
02
b0 "
b0 1
b10000000000000000 !
b10000000000000000 0
b10000000000000000 C
b10000000000000000 Q
0U
04
b10000000000000000 E
b10000000000000000 I
b10000000000000000 N
b11111111111111111111111111111110 ,
b11111111111111111111111111111110 ;
0S
b1 3
b1 9
b1 =
b1111111111111111 .
b1111111111111111 A
b1111111111111111 K
b10000000000000000 5
b10000000000000000 8
b10000000000000000 >
b10000000000000000 ?
b10000000000000000 F
b10000000000000000 G
b1 %
b1 (
b1 :
b1111111111111111 #
b1111111111111111 &
b1111111111111111 6
#40
b110 "
b110 1
0-
14
b0 !
b0 0
b0 C
b0 Q
12
b0 D
b0 M
b0 O
b0 E
b0 I
b0 N
1<
17
1T
1H
1L
b11111111111111111111111111111111 ,
b11111111111111111111111111111111 ;
b11111111111111111111111111111111 3
b11111111111111111111111111111111 9
b11111111111111111111111111111111 =
b0 )
b0 @
b0 J
b0 .
b0 A
b0 K
b0 5
b0 8
b0 >
b0 ?
b0 F
b0 G
b1 $
b1 '
b1 B
b0 %
b0 (
b0 :
b0 #
b0 &
b0 6
#50
b10 "
b10 1
b1111111111111111 !
b1111111111111111 0
b1111111111111111 C
b1111111111111111 Q
b11111111111111111111111111111110 3
b11111111111111111111111111111110 9
b11111111111111111111111111111110 =
b10000000000000001 D
b10000000000000001 M
b10000000000000001 O
b1111111111111111 E
b1111111111111111 I
b1111111111111111 N
b11111111111111111111111111111110 ,
b11111111111111111111111111111110 ;
b10000000000000001 .
b10000000000000001 A
b10000000000000001 K
b1111111111111111 5
b1111111111111111 8
b1111111111111111 >
b1111111111111111 ?
b1111111111111111 F
b1111111111111111 G
b1 %
b1 (
b1 :
b10000000000000000 #
b10000000000000000 &
b10000000000000000 6
#60
1-
b1000 "
b1000 1
0+
02
b11111111111111111111111111111111 !
b11111111111111111111111111111111 0
b11111111111111111111111111111111 C
b11111111111111111111111111111111 Q
b11111111111111111111111111111111 3
b11111111111111111111111111111111 9
b11111111111111111111111111111111 =
b11111111111111111111111111111111 D
b11111111111111111111111111111111 M
b11111111111111111111111111111111 O
b11111111111111111111111111111110 E
b11111111111111111111111111111110 I
b11111111111111111111111111111110 N
0<
07
0T
0H
0L
1P
b0 ,
b0 ;
1S
b11111111111111111111111111111111 )
b11111111111111111111111111111111 @
b11111111111111111111111111111111 J
b11111111111111111111111111111111 .
b11111111111111111111111111111111 A
b11111111111111111111111111111111 K
1R
b11111111111111111111111111111110 5
b11111111111111111111111111111110 8
b11111111111111111111111111111110 >
b11111111111111111111111111111110 ?
b11111111111111111111111111111110 F
b11111111111111111111111111111110 G
b10 $
b10 '
b10 B
b11111111111111111111111111111111 %
b11111111111111111111111111111111 (
b11111111111111111111111111111111 :
b11111111111111111111111111111111 #
b11111111111111111111111111111111 &
b11111111111111111111111111111111 6
#70
b0 "
b0 1
0-
1/
b1110111010000110011010001110111 !
b1110111010000110011010001110111 0
b1110111010000110011010001110111 C
b1110111010000110011010001110111 Q
12
b1110111010000110011010001110110 E
b1110111010000110011010001110110 I
b1110111010000110011010001110110 N
b1110111010000110011010001110111 D
b1110111010000110011010001110111 M
b1110111010000110011010001110111 O
1U
b1110111010000110011010001110110 5
b1110111010000110011010001110110 8
b1110111010000110011010001110110 >
b1110111010000110011010001110110 ?
b1110111010000110011010001110110 F
b1110111010000110011010001110110 G
b10001000101111001100101110001000 ,
b10001000101111001100101110001000 ;
b1110111010000110011010001110111 )
b1110111010000110011010001110111 @
b1110111010000110011010001110111 J
0S
b1110111010000110011010001110111 3
b1110111010000110011010001110111 9
b1110111010000110011010001110111 =
b1110111010000110011010001110111 %
b1110111010000110011010001110111 (
b1110111010000110011010001110111 :
#80
b100 "
b100 1
b0 !
b0 0
b0 C
b0 Q
b0 D
b0 M
b0 O
1/
b11111111111111111111111111111111 E
b11111111111111111111111111111111 I
b11111111111111111111111111111111 N
b0 ,
b0 ;
1S
b11111111111111111111111111111111 3
b11111111111111111111111111111111 9
b11111111111111111111111111111111 =
b0 )
b0 @
b0 J
0R
b11111111111111111111111111111111 5
b11111111111111111111111111111111 8
b11111111111111111111111111111111 >
b11111111111111111111111111111111 ?
b11111111111111111111111111111111 F
b11111111111111111111111111111111 G
04
b11111111111111111111111111111111 %
b11111111111111111111111111111111 (
b11111111111111111111111111111111 :
b0 #
b0 &
b0 6
#90
0/
0*
b1 E
b1 I
b1 N
1-
b1000 "
b1000 1
b11111111111111111111111111111111 !
b11111111111111111111111111111111 0
b11111111111111111111111111111111 C
b11111111111111111111111111111111 Q
b0 3
b0 9
b0 =
b1 5
b1 8
b1 >
b1 ?
b1 F
b1 G
04
02
b11111111111111111111111111111111 D
b11111111111111111111111111111111 M
b11111111111111111111111111111111 O
1<
17
1T
1H
1L
b11 $
b11 '
b11 B
