Archive/WiSe_2022_2023/TechnischeInformatik/submissions/submission_22_11_21_dressler_kroehl_halank/src/xor_3.sv
/**
 *3 Input xor (because we don't use bitwise operators apperantly)
 **/
module xor_3 ( input  logic i_in0,
                            i_in1,
                            i_in2,
               output logic o_res );
    logic l_xor0;
    xor xor_0 (l_xor0, i_in0, i_in1);
    xor xor_1 (o_res, l_xor0, i_in2);
endmodule

Archive/WiSe_2022_2023/TechnischeInformatik/submissions/submission_22_11_21_dressler_kroehl_halank/src/xor_3_tb.sv
/**
 * Testbench for 3 Input XOR Gate
 **/
module xor_3_tb;

    logic l_in0, l_in1, l_in2, l_res;

    xor_3 m_dut (.i_in0(l_in0), .i_in1(l_in1), .i_in2(l_in2), .o_res(l_res));

    initial begin
        $dumpfile("xor_3_tb.vcd");
        $dumpvars;

        l_in0 = 0;
        l_in1 = 0;
        l_in2 = 0;
        #10;
        assert(l_res === 0);

        l_in0 = 0;
        l_in1 = 0;
        l_in2 = 1;
        #10;
        assert(l_res === 1);

        l_in0 = 0;
        l_in1 = 1;
        l_in2 = 0;
        #10;
        assert(l_res === 1);

        l_in0 = 1;
        l_in1 = 0;
        l_in2 = 0;
        #10;
        assert(l_res === 1);

        l_in0 = 0;
        l_in1 = 1;
        l_in2 = 1;
        #10;
        assert(l_res === 0);

        l_in0 = 1;
        l_in1 = 0;
        l_in2 = 1;
        #10;
        assert(l_res === 0);

        l_in0 = 1;
        l_in1 = 1;
        l_in2 = 0;
        #10;
        assert(l_res === 0);

        l_in0 = 1;
        l_in1 = 1;
        l_in2 = 1;
        #10;
        assert(l_res === 1);
        $finish;
    end


endmodule

Archive/WiSe_2022_2023/TechnischeInformatik/submissions/submission_22_11_21_dressler_kroehl_halank/src/xor_3_tb.vcd
$date
	Tue Nov 15 16:45:39 2022
$end
$version
	Icarus Verilog
$end
$timescale
	1s
$end
$scope module xor_3_tb $end
$var wire 1 ! l_res $end
$var reg 1 " l_in0 $end
$var reg 1 # l_in1 $end
$var reg 1 $ l_in2 $end
$scope module m_dut $end
$var wire 1 " i_in0 $end
$var wire 1 # i_in1 $end
$var wire 1 $ i_in2 $end
$var wire 1 % l_xor0 $end
$var wire 1 ! o_res $end
$upscope $end
$upscope $end
$enddefinitions $end
#0
$dumpvars
0%
0$
0#
0"
0!
$end
#10
1!
1$
#20
1%
0$
1#
#30
0#
1"
#40
0!
1$
1#
0"
#50
0#
1"
#60
0%
0$
1#
#70
1!
1$
