Archive/WiSe_2022_2023/TechnischeInformatik/submissions/submission_22_11_28_dressler_kroehl_halank/src/sr_latch.sv
/**
SR Latch
@param i_r reset input
@param i_s set input
@param o_q state output
@param o_nq inverted state output
**/
module sr_latch(
    input logic i_r, 
    input logic i_s, 
    output logic o_q, 
    output logic o_qn);

    nor m_nor_0(o_q, i_r, o_qn);
    nor m_nor_1(o_qn, i_s, o_q);

endmodule

Archive/WiSe_2022_2023/TechnischeInformatik/submissions/submission_22_11_28_dressler_kroehl_halank/src/d_latch.sv
/**
D Latch consisting of 2 SR-Latches
@param i_clk clock input
@param i_d Data input
@param o_q Q output
@param o_qn Q inverted output
*/
module d_latch(
    input logic i_clk, 
    input logic i_d, 
    output logic o_q, 
    output logic o_qn);

    logic l_dn, l_r, l_s;
    not m_not_0(l_dn, i_d);

    and m_and_0(l_r, i_clk, l_dn);
    and m_and_1(l_s, i_clk, i_d);

    sr_latch m_sr_latch_0(.i_s(l_s), .i_r(l_r), .o_q(o_q), .o_qn(o_qn));

endmodule

Archive/WiSe_2022_2023/TechnischeInformatik/submissions/submission_22_11_28_dressler_kroehl_halank/src/d_flip_flop.sv
/**
Rising Edge D Flipflop consisting of 2 D Latches
@param clk clock input
@param d data input
@param q output
@param qn inverted output
*/
module d_flip_flop(
    input logic i_clk,
    input logic i_d,
    output logic o_q,
    output logic o_qn
);
    logic l_clkn, l_x;

    not m_not_0(l_clkn, i_clk);

    d_latch m_d_latch_0(.i_clk(l_clkn), .i_d(i_d), .o_q(l_x));
    d_latch m_d_latch_1(.i_clk(i_clk), .i_d(l_x), .o_q(o_q), .o_qn(o_qn));

endmodule

Archive/WiSe_2022_2023/TechnischeInformatik/submissions/submission_22_11_28_dressler_kroehl_halank/src/mux_2.sv
/**
 *2er Mux für N bits
 **/
module mux_2 #(parameter N=64) ( input  logic [N-1:0] i_in0,
                                                   i_in1,
                              input  logic         i_s,
                              output logic [N-1:0] o_out );
    always_comb
    begin
        case(i_s)
            1'b0: o_out = i_in0;
            1'b1: o_out = i_in1;
            default: o_out = 1'bx;
        endcase
    end

endmodule

Archive/WiSe_2022_2023/TechnischeInformatik/submissions/submission_22_11_28_dressler_kroehl_halank/src/d_flip_flop_en.sv
/**
rising edge d flip flop with enable signal
*/
module d_flip_flop_en(
    input logic i_clk,
    input logic i_d,
    input logic i_en,
    output logic o_q,
    output logic o_qn
);

    logic l_mux;
    mux_2 #(.N(1)) m_mux_2_0(.i_in0(o_q), .i_in1(i_d), .i_s(i_en), .o_out(l_mux));

    d_flip_flop d_flip_flop_0(.i_clk(i_clk), .i_d(l_mux), .o_q(o_q), .o_qn(o_qn));

endmodule

Archive/WiSe_2022_2023/TechnischeInformatik/submissions/submission_22_11_28_dressler_kroehl_halank/src/d_flip_flop_en_tb.sv
/**
 *Testbench for d_flip_flop_en
 **/
module d_flip_flop_en_tb;
    logic l_clk, l_d, l_en, l_q, l_qn;

    d_flip_flop_en m_dut(.i_clk(l_clk), .i_d(l_d), .i_en(l_en), .o_q(l_q), .o_qn(l_qn));

    always begin // clock with period #10
        l_clk <= 1'b1;
        #5;
        l_clk <= 1'b0;
        #5;
    end

    initial begin
        $dumpfile("d_flip_flop_en_tb.vcd");
        $dumpvars;
    
        l_d = 1'b0;
        l_en = 1'b1;
        #11;
        assert(l_q === 1'b0);
        assert(l_qn === 1'b1);

        l_d = 1'b1;
        l_en = 1'b1;
        #10;
        assert(l_q === 1'b1);
        assert(l_qn === 1'b0);

        l_en = 1'b0;
        #1;
        l_d = 1'b0;
        #9;
        assert(l_q === 1'b1);
        assert(l_qn === 1'b0);

        l_en = 1'b1;
        #10;
        assert(l_q === 1'b0);
        assert(l_qn === 1'b1);
        
        $finish;
    end
endmodule

Archive/WiSe_2022_2023/TechnischeInformatik/submissions/submission_22_11_28_dressler_kroehl_halank/src/d_flip_flop_en_tb.vcd
$date
	Tue Nov 22 16:17:30 2022
$end
$version
	Icarus Verilog
$end
$timescale
	1s
$end
$scope module d_flip_flop_en_tb $end
$var wire 1 ! l_qn $end
$var wire 1 " l_q $end
$var reg 1 # l_clk $end
$var reg 1 $ l_d $end
$var reg 1 % l_en $end
$scope module m_dut $end
$var wire 1 # i_clk $end
$var wire 1 $ i_d $end
$var wire 1 % i_en $end
$var wire 1 ! o_qn $end
$var wire 1 " o_q $end
$var wire 1 & l_mux $end
$scope module d_flip_flop_0 $end
$var wire 1 # i_clk $end
$var wire 1 ' l_clkn $end
$var wire 1 ! o_qn $end
$var wire 1 " o_q $end
$var wire 1 ( l_x $end
$var wire 1 & i_d $end
$scope module m_d_latch_0 $end
$var wire 1 ' i_clk $end
$var wire 1 ) l_dn $end
$var wire 1 * l_r $end
$var wire 1 + l_s $end
$var wire 1 , o_qn $end
$var wire 1 ( o_q $end
$var wire 1 & i_d $end
$scope module m_sr_latch_0 $end
$var wire 1 * i_r $end
$var wire 1 + i_s $end
$var wire 1 ( o_q $end
$var wire 1 , o_qn $end
$upscope $end
$upscope $end
$scope module m_d_latch_1 $end
$var wire 1 # i_clk $end
$var wire 1 ( i_d $end
$var wire 1 - l_dn $end
$var wire 1 . l_r $end
$var wire 1 / l_s $end
$var wire 1 ! o_qn $end
$var wire 1 " o_q $end
$scope module m_sr_latch_0 $end
$var wire 1 . i_r $end
$var wire 1 / i_s $end
$var wire 1 " o_q $end
$var wire 1 ! o_qn $end
$upscope $end
$upscope $end
$upscope $end
$scope module m_mux_2_0 $end
$var wire 1 " i_in0 $end
$var wire 1 $ i_in1 $end
$var wire 1 % i_s $end
$var reg 1 & o_out $end
$upscope $end
$upscope $end
$upscope $end
$enddefinitions $end
#0
$dumpvars
x/
x.
x-
x,
0+
0*
1)
x(
0'
0&
1%
0$
1#
x"
x!
$end
#5
1,
1-
0(
1*
1'
0.
0/
0#
#10
1!
0*
0"
0'
1.
1#
#11
0)
1&
1$
#15
0-
1(
0,
1+
1'
0.
0#
#20
1"
0+
0!
0'
1/
1#
#21
0%
#22
0$
#25
1+
1'
0/
0#
#30
0+
0'
1/
1#
#31
1)
0&
1%
#35
1,
1-
0(
1*
1'
0/
0#
#40
1!
0*
0"
0'
1.
1#
