Archive/WiSe_2022_2023/TechnischeInformatik/submissions/submission_22_11_28_dressler_kroehl_halank/src/sr_latch.sv
/**
SR Latch
@param i_r reset input
@param i_s set input
@param o_q state output
@param o_nq inverted state output
**/
module sr_latch(
    input logic i_r, 
    input logic i_s, 
    output logic o_q, 
    output logic o_qn);

    nor m_nor_0(o_q, i_r, o_qn);
    nor m_nor_1(o_qn, i_s, o_q);

endmodule

Archive/WiSe_2022_2023/TechnischeInformatik/submissions/submission_22_11_28_dressler_kroehl_halank/src/d_latch.sv
/**
D Latch consisting of 2 SR-Latches
@param i_clk clock input
@param i_d Data input
@param o_q Q output
@param o_qn Q inverted output
*/
module d_latch(
    input logic i_clk, 
    input logic i_d, 
    output logic o_q, 
    output logic o_qn);

    logic l_dn, l_r, l_s;
    not m_not_0(l_dn, i_d);

    and m_and_0(l_r, i_clk, l_dn);
    and m_and_1(l_s, i_clk, i_d);

    sr_latch m_sr_latch_0(.i_s(l_s), .i_r(l_r), .o_q(o_q), .o_qn(o_qn));

endmodule

Archive/WiSe_2022_2023/TechnischeInformatik/submissions/submission_22_11_28_dressler_kroehl_halank/src/d_latch_tb.sv
/**
 *Testbench for d_latch
 **/
module d_latch_tb;
    logic l_clk, l_d, l_q, l_qn;

    d_latch m_dut(.i_clk(l_clk), .i_d(l_d), .o_q(l_q), .o_qn(l_qn));

    always begin // clock with period #10
        l_clk <= 1'b1;
        #5;
        l_clk <= 1'b0;
        #5;
    end

    initial begin
        $dumpfile("d_latch_tb.vcd");
        $dumpvars;
        l_d = 1'b0;
        #10;
        assert(l_q === 1'b0);
        assert(l_qn === 1'b1);

        l_d = 1'b1;
        #10;
        assert(l_q === 1'b1);
        assert(l_qn === 1'b0);

        #6; //clock low
        l_d = 1'b0;
        #2;
        assert(l_q === 1'b1);
        assert(l_qn === 1'b0);

        #12; //full clock cycle
        assert(l_q === 1'b0);
        assert(l_qn === 1'b1);

        $finish;
    end
endmodule

Archive/WiSe_2022_2023/TechnischeInformatik/submissions/submission_22_11_28_dressler_kroehl_halank/src/d_latch_tb.vcd
$date
	Tue Nov 22 15:48:56 2022
$end
$version
	Icarus Verilog
$end
$timescale
	1s
$end
$scope module d_latch_tb $end
$var wire 1 ! l_qn $end
$var wire 1 " l_q $end
$var reg 1 # l_clk $end
$var reg 1 $ l_d $end
$scope module m_dut $end
$var wire 1 # i_clk $end
$var wire 1 $ i_d $end
$var wire 1 % l_dn $end
$var wire 1 & l_r $end
$var wire 1 ' l_s $end
$var wire 1 ! o_qn $end
$var wire 1 " o_q $end
$scope module m_sr_latch_0 $end
$var wire 1 & i_r $end
$var wire 1 ' i_s $end
$var wire 1 " o_q $end
$var wire 1 ! o_qn $end
$upscope $end
$upscope $end
$upscope $end
$enddefinitions $end
#0
$dumpvars
0'
1&
1%
0$
1#
0"
1!
$end
#5
0&
0#
#10
1"
0!
1'
1#
0%
1$
#15
0'
0#
#20
1'
1#
#25
0'
0#
#26
1%
0$
#30
1!
0"
1&
1#
#35
0&
0#
#40
1&
1#
