Archive/WiSe_2022_2023/TechnischeInformatik/submissions/submission_22_12_05_dressler_kroehl_halank/src/clock.sv
/**
 * Outputs a clock signal based on the given rollover signal.
 * The clock signal changes on every positive edge of the rollover signal.
 * On a positive edge of the reset signal, the clock is reset to high.
 *
 * @param i_roll_over rollover signal.
 * @param i_reset reset signal.
 * @param o_clk set to generated clock signal.
 **/
module clock( input  logic i_roll_over,
              input  logic i_reset,
              output logic o_clk );
  logic m_clk;

  always_ff @(posedge i_roll_over , posedge i_reset)
  begin
    if (i_reset)
      begin
        m_clk <= 1'b1;
      end
    else
      begin
       if (i_roll_over)
        begin
          m_clk <= ~m_clk;
        end
      end
  end

  assign o_clk = m_clk;
endmodule

Archive/WiSe_2022_2023/TechnischeInformatik/submissions/submission_22_12_05_dressler_kroehl_halank/src/clock_tb.sv
/**
 * Testbench of the clock derived from a counter's rollover signal.
 **/
module clock_tb;
  logic l_reset;
  logic l_clk;
  logic l_roll_over;

  // reset
  initial
    begin
      l_reset <= 1;
      #4;
      l_reset <= 0;
    end

  // rollover T=#20
  always begin
      l_roll_over <= 1;
      #2;
      l_roll_over <= 0;
      #8;
  end

  //clock T=#20
  clock dut( .i_roll_over(l_roll_over),
             .i_reset(l_reset),
             .o_clk(l_clk) );

  initial begin
    $dumpfile("dump_clock.vcd");
    $dumpvars;

    #5;
    assert( l_clk === 1'b1 );
    #10;
    assert( l_clk === 1'b0 );
    #10;
    assert( l_clk === 1'b1 );
    #10;
    assert( l_clk === 1'b0 );
    #10;
    assert( l_clk === 1'b1 );
    #10;
    assert( l_clk === 1'b0 );
    #10;

    $finish;
  end
endmodule

Archive/WiSe_2022_2023/TechnischeInformatik/submissions/submission_22_12_05_dressler_kroehl_halank/src/dump_clock.vcd
$date
	Wed Nov 30 02:22:01 2022
$end
$version
	Icarus Verilog
$end
$timescale
	1s
$end
$scope module clock_tb $end
$var wire 1 ! l_clk $end
$var reg 1 " l_reset $end
$var reg 1 # l_roll_over $end
$scope module dut $end
$var wire 1 " i_reset $end
$var wire 1 # i_roll_over $end
$var wire 1 ! o_clk $end
$var reg 1 $ m_clk $end
$upscope $end
$upscope $end
$enddefinitions $end
#0
$dumpvars
1$
1#
1"
1!
$end
#2
0#
#4
0"
#10
0!
0$
1#
#12
0#
#20
1!
1$
1#
#22
0#
#30
0!
0$
1#
#32
0#
#40
1!
1$
1#
#42
0#
#50
0!
0$
1#
#52
0#
#60
1!
1$
1#
#62
0#
