Archive/WiSe_2022_2023/TechnischeInformatik/submissions/submission_22_12_05_dressler_kroehl_halank/src/counter_mod_k_count.sv
/**
 * Counter which has the number of elapsed clock cycles modulo k as output.
 *
 * @param i_clk input clock.
 * @param i_reset reset signal which resets the counter's value to zero.
 * @param i_k value k which is used for the modulo computation.
 * @param o_count set to number of elapsed clock cycles modulo k.
 **/
module counter_mod_k_count #(parameter N=8) ( input  logic         i_clk,
                                              input  logic         i_reset,
                                              input  logic [N-1:0] i_k,
                                              output logic [N-1:0] o_count );
  // current value of the counter
  logic [N-1:0] m_count;

  // on positive edge of input clock or reset
  // either reset counter or assign next value
  always_ff @(posedge i_clk, posedge i_reset)
    begin
      if( i_reset == 1'b1 )
        begin
          m_count <= {N{1'b0}};
        end
      else
        begin
          if( m_count == i_k-1 )
            begin
              m_count <= {N{1'b0}};
            end
          else
            begin
              m_count <= m_count + 1;
            end
        end
    end

  // assign output bus
  assign o_count = m_count;
endmodule

Archive/WiSe_2022_2023/TechnischeInformatik/submissions/submission_22_12_05_dressler_kroehl_halank/src/counter_mod_k_count_tb.sv
/**
 * Testbench of the modulo-k counter which has number of elapsed clock cycles as output.
 **/
module counter_mod_k_count_tb;
  logic l_clk;
  logic l_reset;

  logic [1:0] l_count;
  logic [1:0] l_k;
  assign l_k = 2'b11;

  // reset
  initial
    begin
      l_reset <= 1;
      #3;
      l_reset <= 0;
    end

  // clock
  always
    begin
      l_clk <= 1;
      #5;
      l_clk <= 0;
      #5;
    end

  counter_mod_k_count #(2) dut( l_clk,
                                l_reset,
                                l_k,
                                l_count );

  initial begin
    $dumpfile("dump_counter_mod_k_count.vcd");
    $dumpvars;

    #5;
    assert( l_count === 3'd0 );
    #10;
    assert( l_count === 3'd1 );
    #10;
    assert( l_count === 3'd2 );
    #10;
    assert( l_count === 3'd0 );
    #10;
    assert( l_count === 3'd1 );
    #10;
    assert( l_count === 3'd2 );
    #10;
    assert( l_count === 3'd0 );
    #10;
    assert( l_count === 3'd1 );
    #10;
    assert( l_count === 3'd2 );

    $finish;
  end
endmodule

Archive/WiSe_2022_2023/TechnischeInformatik/submissions/submission_22_12_05_dressler_kroehl_halank/src/dump_counter_mod_k_count.vcd
$date
	Tue Nov 29 13:09:12 2022
$end
$version
	Icarus Verilog
$end
$timescale
	1s
$end
$scope module counter_mod_k_count_tb $end
$var wire 2 ! l_k [1:0] $end
$var wire 2 " l_count [1:0] $end
$var reg 1 # l_clk $end
$var reg 1 $ l_reset $end
$scope module dut $end
$var wire 1 # i_clk $end
$var wire 2 % i_k [1:0] $end
$var wire 1 $ i_reset $end
$var wire 2 & o_count [1:0] $end
$var reg 2 ' m_count [1:0] $end
$upscope $end
$upscope $end
$enddefinitions $end
#0
$dumpvars
b0 '
b0 &
b11 %
1$
1#
b0 "
b11 !
$end
#3
0$
#5
0#
#10
b1 "
b1 &
b1 '
1#
#15
0#
#20
b10 "
b10 &
b10 '
1#
#25
0#
#30
b0 "
b0 &
b0 '
1#
#35
0#
#40
b1 "
b1 &
b1 '
1#
#45
0#
#50
b10 "
b10 &
b10 '
1#
#55
0#
#60
b0 "
b0 &
b0 '
1#
#65
0#
#70
b1 "
b1 &
b1 '
1#
#75
0#
#80
b10 "
b10 &
b10 '
1#
