Archive/WiSe_2022_2023/TechnischeInformatik/submissions/submission_22_12_05_dressler_kroehl_halank/src/counter_mod_k_ro.sv
/**
 * Counter which has the rollover signal as output.
 * The signal o_roll_over is high in every clock cycle after a rollover occurred and low in all other cycles.
 *
 * Assume k=3, then:
 * cycle     | 0 | 1 | 2 | 3 | 4 | 5 | 6 | 7 | 8 | 9 | 10 | ...
 * mod k     | 0 | 1 | 2 | 0 | 1 | 2 | 0 | 1 | 2 | 0 |  1 | ...
 * rollover: | 0 | 0 | 0 | 1 | 0 | 0 | 1 | 0 | 0 | 1 |  0 | ...
 *
 *
 * @param i_clk input clock.
 * @param i_reset reset signal which resets the counter's value to zero.
 * @param i_k value k which is used for the modulo computation.
 * @param o_roll_over set to rollover signal which is high in every clock cycle after a rollover occurred; low else.
 **/
module counter_mod_k_ro #(parameter N=8) ( input  logic         i_clk,
                                           input  logic         i_reset,
                                           input  logic [N-1:0] i_k,
                                           output logic         o_roll_over );
  // value of the counter
  logic [N-1:0] m_count;
  always_ff @(posedge i_clk, posedge i_reset)
  begin
    if(i_reset == 1'b1 )
      begin
        m_count <= {N{1'b0}};
        o_roll_over <= 1'b0;
      end
    else
      begin
        if( m_count == i_k-1 )
          begin
            m_count <= {N{1'b0}};
            o_roll_over <= 1'b1;
          end
        else
          begin
            m_count <= m_count + 1;
            o_roll_over <= 1'b0;
          end 
      end
  end

endmodule

Archive/WiSe_2022_2023/TechnischeInformatik/submissions/submission_22_12_05_dressler_kroehl_halank/src/counter_mod_k_ro_tb.sv
/**
 * Testbench of the modulo-k counter which has the rollover signal as output.
 **/
module counter_mod_k_ro_tb;
  logic l_clk;
  logic l_reset;

  logic l_roll_over;
  logic [2:0] l_k;
  assign l_k = 3'b100;

  // clock
  always begin
      l_clk <= 1;
      #5;
      l_clk <= 0;
      #5;
  end

  // reset
  initial
    begin
      l_reset <= 1;
      #4;
      l_reset <= 0;
    end

  counter_mod_k_ro #(.N(3)) dut( l_clk,
                                l_reset,
                                l_k,
                                l_roll_over );

   initial begin
    $dumpfile("dump_counter_mod_k_ro.vcd");
    $dumpvars;

    #5;
    assert( l_roll_over === 1'b0 );
    #10;
    assert( l_roll_over === 1'b0 );
    #10;
    assert( l_roll_over === 1'b0 );
    #10;
    assert( l_roll_over === 1'b0 );
    #10;
    assert( l_roll_over === 1'b1 );
    #10;
    assert( l_roll_over === 1'b0 );
    #10;
    assert( l_roll_over === 1'b0 );
    #10;
    assert( l_roll_over === 1'b0 );
    #10;
    assert( l_roll_over === 1'b1 );
    #10;
    assert( l_roll_over === 1'b0 )
    #10;
  
    $finish;
  end
endmodule

Archive/WiSe_2022_2023/TechnischeInformatik/submissions/submission_22_12_05_dressler_kroehl_halank/src/dump_counter_mod_k_ro.vcd
$date
	Wed Nov 30 02:23:01 2022
$end
$version
	Icarus Verilog
$end
$timescale
	1s
$end
$scope module counter_mod_k_ro_tb $end
$var wire 3 ! l_k [2:0] $end
$var wire 1 " l_roll_over $end
$var reg 1 # l_clk $end
$var reg 1 $ l_reset $end
$scope module dut $end
$var wire 1 # i_clk $end
$var wire 3 % i_k [2:0] $end
$var wire 1 $ i_reset $end
$var reg 3 & m_count [2:0] $end
$var reg 1 " o_roll_over $end
$upscope $end
$upscope $end
$enddefinitions $end
#0
$dumpvars
b0 &
b100 %
1$
1#
0"
b100 !
$end
#4
0$
#5
0#
#10
b1 &
1#
#15
0#
#20
b10 &
1#
#25
0#
#30
b11 &
1#
#35
0#
#40
b0 &
1"
1#
#45
0#
#50
b1 &
0"
1#
#55
0#
#60
b10 &
1#
#65
0#
#70
b11 &
1#
#75
0#
#80
b0 &
1"
1#
#85
0#
#90
b1 &
0"
1#
#95
0#
#100
b10 &
1#
