Archive/WiSe_2022_2023/TechnischeInformatik/submissions/submission_22_11_14_dressler_kroehl_halank/src/full_adder.sv
/**
 * Gate-level implementation of a full adder.
 *
 * @param i_a input A.
 * @param i_b input B.
 * @param i_carry_in carry in.
 * @param o_s sum.
 * @param o_carry_out carry out.
 **/
module full_adder( input  logic i_a,
                                i_b,
                                i_carry_in,
                   output logic o_s,
                                o_carry_out );

    logic l_ab, l_bc, l_ca;
    xor m_xor_0( o_s, i_a, i_b, i_carry_in );
    and m_and_0( l_ab, i_a, i_b );
    and m_and_1( l_bc, i_b, i_carry_in );
    and m_and_2( l_ca, i_carry_in, i_a );
    or m_or_0( o_carry_out, l_ab, l_bc, l_ca );
endmodule

Archive/WiSe_2022_2023/TechnischeInformatik/submissions/submission_22_11_07_dressler_kroehl_halank/src/full_adder_tb.sv
/**
 * Testbench of the gate-level full adder.
 */
module full_adder_tb;
  logic l_a, l_b, l_s;
  logic l_carry_in, l_carry_out;

  full_adder m_dut( .i_a(         l_a         ),
                    .i_b(         l_b         ),
                    .i_carry_in(  l_carry_in  ),
                    .o_s(         l_s         ),
                    .o_carry_out( l_carry_out ) );

  initial begin
    $dumpfile("dump_full_adder.vcd");
    $dumpvars;

    l_a = 1'b0;
    l_b = 1'b0;
    l_carry_in = 1'b0;
    #10;
    assert( l_s === 1'b0 );
    assert( l_carry_out === 1'b0 );

    l_a = 1'b1;
    l_b = 1'b0;
    l_carry_in = 1'b0;
    #10;
    assert( l_s === 1'b1 );
    assert( l_carry_out === 1'b0 );

    l_a = 1'b0;
    l_b = 1'b1;
    l_carry_in = 1'b0;
    #10;
    assert( l_s === 1'b1 );
    assert( l_carry_out === 1'b0 );

    l_a = 1'b0;
    l_b = 1'b0;
    l_carry_in = 1'b1;
    #10;
    assert( l_s === 1'b1 );
    assert( l_carry_out === 1'b0 );

    l_a = 1'b1;
    l_b = 1'b1;
    l_carry_in = 1'b0;
    #10;
    assert( l_s === 1'b0 );
    assert( l_carry_out === 1'b1 );

    l_a = 1'b1;
    l_b = 1'b0;
    l_carry_in = 1'b1;
    #10;
    assert( l_s === 1'b0 );
    assert( l_carry_out === 1'b1 );

    l_a = 1'b0;
    l_b = 1'b1;
    l_carry_in = 1'b1;
    #10;
    assert( l_s === 1'b0 );
    assert( l_carry_out === 1'b1 );

    l_a = 1'b1;
    l_b = 1'b1;
    l_carry_in = 1'b1;
    #10;
    assert( l_s === 1'b1 );
    assert( l_carry_out === 1'b1 );

    $finish;
  end
endmodule

Archive/WiSe_2022_2023/TechnischeInformatik/submissions/submission_22_11_07_dressler_kroehl_halank/src/dump_full_adder.vcd
$date
	Wed Nov  2 16:52:30 2022
$end
$version
	Icarus Verilog
$end
$timescale
	1s
$end
$scope module full_adder_tb $end
$var wire 1 ! l_s $end
$var wire 1 " l_carry_out $end
$var reg 1 # l_a $end
$var reg 1 $ l_b $end
$var reg 1 % l_carry_in $end
$scope module m_dut $end
$var wire 1 # i_a $end
$var wire 1 $ i_b $end
$var wire 1 % i_carry_in $end
$var wire 1 & l_ab $end
$var wire 1 ' l_bc $end
$var wire 1 ( l_ca $end
$var wire 1 " o_carry_out $end
$var wire 1 ! o_s $end
$upscope $end
$upscope $end
$enddefinitions $end
#0
$dumpvars
0(
0'
0&
0%
0$
0#
0"
0!
$end
#10
1!
1#
#20
1$
0#
#30
1%
0$
#40
1"
0!
1&
0%
1$
1#
#50
1(
0&
1%
0$
#60
1'
0(
1$
0#
#70
1!
1&
1(
1#
